LICENSE
MANIFEST.in
README.rst
setup.py
bigautohack/__init__.py
bigautohack/management/__init__.py
bigautohack/management/commands/__init__.py
bigautohack/management/commands/bigautohack.py
django_bigautohack.egg-info/PKG-INFO
django_bigautohack.egg-info/SOURCES.txt
django_bigautohack.egg-info/dependency_links.txt
django_bigautohack.egg-info/top_level.txt