Metadata-Version: 1.1
Name: django-bigautohack
Version: 0.1
Summary: Nice working solution to make up for the absence of BigAutoField in django (#14286).
Home-page: https://github.com/Remiremi/django_bigautohack
Author: Rémi Koenig
Author-email: remi.koenig@gmail.com
License: BSD License
Platform: UNKNOWN
Classifier: Environment :: Web Environment
Classifier: Framework :: Django
Classifier: Intended Audience :: Developers
Classifier: License :: OSI Approved :: MIT License
Classifier: Operating System :: OS Independent
Classifier: Programming Language :: Python
Classifier: Programming Language :: Python :: 2
Classifier: Programming Language :: Python :: 2.6
Classifier: Programming Language :: Python :: 2.7
Classifier: Programming Language :: Python :: 3
Classifier: Programming Language :: Python :: 3.3
